hadoop/__init__.py
hadoop/httputil.py
hadoop/httputil2.py
hadoop/httputil3.py
hadoop/yarn.py
hadoop_yarn_rest_api-1.1.0.dist-info/LICENSE
hadoop_yarn_rest_api-1.1.0.dist-info/METADATA
hadoop_yarn_rest_api-1.1.0.dist-info/WHEEL
hadoop_yarn_rest_api-1.1.0.dist-info/top_level.txt
hadoop_yarn_rest_api-1.1.0.dist-info/RECORD
