Metadata-Version: 2.1
Name: hadoop-yarn-rest-api
Version: 1.1.0
Summary: Python wrapper for Hadoop YARN REST API
Home-page: https://github.com/developer-sdk/yarn-rest-api
Author: hs_seo
Author-email: fluorite118@gmail.com
License: MIT
Download-URL: https://github.com/developer-sdk/yarn-rest-api/archive/master.zip
Keywords: hadoop,yarn,rest,api,resourcemanager
Platform: UNKNOWN
Classifier: Programming Language :: Python :: 2
Classifier: Programming Language :: Python :: 2.6
Classifier: Programming Language :: Python :: 2.7
Classifier: Programming Language :: Python :: 3
Classifier: Programming Language :: Python :: 3.2
Classifier: Programming Language :: Python :: 3.3
Classifier: Programming Language :: Python :: 3.4
Classifier: License :: OSI Approved :: MIT License
Classifier: Operating System :: OS Independent
